config.py
logger.py
main.py
persist.py
summarize.py
models/__init__.py
models/fetch_params.py
models/work_item.py
providers/__init__.py
providers/base.py
providers/jira.py
providers/linear.py
service_integrations/__init__.py
service_integrations/base.py
service_integrations/openai.py
services/__init__.py
services/clean_service.py
services/config_service.py
services/connect_service.py
services/disconnect_service.py
services/report_service.py
services/sync_service.py
utils/__init__.py
utils/lock_utils.py
whatdidido-0.1.5.dist-info/licenses/LICENSE
whatdidido-0.1.5.dist-info/METADATA
whatdidido-0.1.5.dist-info/WHEEL
whatdidido-0.1.5.dist-info/entry_points.txt
whatdidido-0.1.5.dist-info/top_level.txt
whatdidido-0.1.5.dist-info/RECORD
