Metadata-Version: 2.4
Name: whatdidido
Version: 0.1.5
Summary: Track your work across Jira and Linear. Generate AI-powered summaries of your activities.
Author-email: Olivier Morissette <oliviersm199@gmail.com>
License: MIT
Project-URL: Homepage, https://github.com/oliviersm199/whatdididoagain
Project-URL: Repository, https://github.com/oliviersm199/whatdididoagain
Project-URL: Issues, https://github.com/oliviersm199/whatdididoagain/issues
Project-URL: Documentation, https://github.com/oliviersm199/whatdididoagain#readme
Keywords: jira,linear,productivity,work-tracking,ai,openai,cli
Classifier: Development Status :: 4 - Beta
Classifier: Intended Audience :: Developers
Classifier: Intended Audience :: End Users/Desktop
Classifier: License :: OSI Approved :: MIT License
Classifier: Operating System :: OS Independent
Classifier: Programming Language :: Python :: 3
Classifier: Programming Language :: Python :: 3.10
Classifier: Programming Language :: Python :: 3.11
Classifier: Programming Language :: Python :: 3.12
Classifier: Programming Language :: Python :: 3.13
Classifier: Programming Language :: Python :: 3.14
Classifier: Topic :: Office/Business
Classifier: Topic :: Utilities
Classifier: Environment :: Console
Requires-Python: >=3.10
License-File: LICENSE
Requires-Dist: click>=8.0.0
Requires-Dist: filelock>=3.0.0
Requires-Dist: jira>=3.0.0
Requires-Dist: pytz>=2025.2
Requires-Dist: questionary>=2.1.1
Requires-Dist: python-dotenv>=1.1.1
Requires-Dist: pydantic>=2.12.3
Requires-Dist: openai>=2.6.0
Requires-Dist: rich>=13.0.0
Requires-Dist: tiktoken>=0.5.0
Provides-Extra: dev
Requires-Dist: mypy>=1.0.0; extra == "dev"
Requires-Dist: pre-commit>=3.0.0; extra == "dev"
Requires-Dist: black>=24.0.0; extra == "dev"
Requires-Dist: flake8>=7.0.0; extra == "dev"
Requires-Dist: pytest>=8.0.0; extra == "dev"
Requires-Dist: pytest-cov>=6.0.0; extra == "dev"
Dynamic: license-file
